edubot_matrix/__init__.py
edubot_matrix/bot_commands.py
edubot_matrix/callbacks.py
edubot_matrix/config.py
edubot_matrix/errors.py
edubot_matrix/g.py
edubot_matrix/main.py
edubot_matrix/message_responses.py
edubot_matrix/rss.py
edubot_matrix/sample.config.yaml
edubot_matrix/storage.py
edubot_matrix/types.py
edubot_matrix/utils.py
edubot_matrix-0.1.1.dist-info/LICENSES/APACHE2.0
edubot_matrix-0.1.1.dist-info/LICENSES/LICENSE
edubot_matrix-0.1.1.dist-info/METADATA
edubot_matrix-0.1.1.dist-info/WHEEL
edubot_matrix-0.1.1.dist-info/RECORD
